[
  {
    "name": "[AVN]Danko",
    "power": 575052737
  },
  {
    "name": "[ARC]Urek Mazino",
    "power": 430692460
  },
  {
    "name": "[ARC]Enzo",
    "power": 369695915
  },
  {
    "name": "[HOE]Big Mistake",
    "power": 225841679
  },
  {
    "name": "[ARC]Hay",
    "power": 225086462
  },
  {
    "name": "[AVN]Yelkao",
    "power": 180843679
  },
  {
    "name": "[AVN]I AM GROOT",
    "power": 167296809
  },
  {
    "name": "[ARC]Whiskey Bent",
    "power": 161393304
  },
  {
    "name": "[ExU]LordJFK99",
    "power": 159844351
  },
  {
    "name": "[716]Spicy2",
    "power": 158172022
  },
  {
    "name": "[ExU]Captain Scorpion",
    "power": 154677333
  },
  {
    "name": "[ARC]goose",
    "power": 154120673
  },
  {
    "name": "[ARC]Atomu",
    "power": 152827214
  },
  {
    "name": "[ExU]Mr244",
    "power": 150985318
  },
  {
    "name": "[AVN]CANER",
    "power": 148789025
  },
  {
    "name": "[AVN]Blade6o",
    "power": 14653166113
  },
  {
    "name": "[ExU]Top",
    "power": 143152086
  },
  {
    "name": "[HOE]HoHo Rays",
    "power": 141344015
  },
  {
    "name": "[ARC]bugbug",
    "power": 133616714
  },
  {
    "name": "[ARC]Cezar",
    "power": 129826254
  },
  {
    "name": "TAVNJAnakin",
    "power": 6258101286
  },
  {
    "name": "[AVN]e3 0ng? MRAYO 0n23",
    "power": 126199196
  },
  {
    "name": "[ExU]F2H",
    "power": 122276836
  },
  {
    "name": "[AVN]Skyland",
    "power": 122013228
  },
  {
    "name": "[AVN]MikiGs",
    "power": 121425519
  },
  {
    "name": "[AVN]SANCAR",
    "power": 119653129
  },
  {
    "name": "[ExU]Echo",
    "power": 1199106295
  },
  {
    "name": "[ExU]skibidiConsulate",
    "power": 117633732
  },
  {
    "name": "[HOE]Aarones]",
    "power": 116726251
  },
  {
    "name": "[ExU]AyChrono",
    "power": 116607167
  },
  {
    "name": "[ExU]Shaky Ground",
    "power": 115384509
  },
  {
    "name": "[ARC]Assassin",
    "power": 11520830680
  },
  {
    "name": "[ARC]Robot",
    "power": 109671229
  },
  {
    "name": "[ARC]Mili",
    "power": 109050475
  },
  {
    "name": "[ExU]Ralston",
    "power": 108907367
  },
  {
    "name": "[ARC]NoiseBoy",
    "power": 108477101
  },
  {
    "name": "[AVN]Nini36170",
    "power": 294881107
  },
  {
    "name": "[ExU]JoJo9144",
    "power": 105907884
  },
  {
    "name": "[ARC]Vosheld",
    "power": 105141283
  },
  {
    "name": "[HOE]JOEY",
    "power": 104902074
  },
  {
    "name": "[AVN]Cervus",
    "power": 104328352
  },
  {
    "name": "[ExU]Galdarian",
    "power": 104114523
  },
  {
    "name": "[ExU]IKHYAmpun",
    "power": 102847151
  },
  {
    "name": "[ARC]Crazy Wizard",
    "power": 102600761
  },
  {
    "name": "[ExU] &  _ y107",
    "power": 102443115
  },
  {
    "name": "[ARC]Dissolve",
    "power": 101587281
  },
  {
    "name": "[ExU]dddDiesel187",
    "power": 3960931013
  },
  {
    "name": "[ExU]Hyperliquid",
    "power": 101335196
  },
  {
    "name": "[ExU]Jess1124",
    "power": 101330086
  },
  {
    "name": "[ExU]muhanad",
    "power": 2524891012
  },
  {
    "name": "[HOE]Nils",
    "power": 100742719
  },
  {
    "name": "[AVN]Gwendoline",
    "power": 100715850
  },
  {
    "name": "[ExU]Supdeath",
    "power": 100534287
  },
  {
    "name": "[AVN]Devils_ eye",
    "power": 99259597
  },
  {
    "name": "[ExU]Black Angel",
    "power": 98924898
  },
  {
    "name": "[ARC]BoxyBrown",
    "power": 98310522
  },
  {
    "name": "[AVN]NeznaBoh",
    "power": 97567117
  },
  {
    "name": "[AVN]ceBlaze",
    "power": 97286784
  },
  {
    "name": "[ExU]Nyado6",
    "power": 96956695
  },
  {
    "name": "[AVN]Gokcenefe",
    "power": 96736799
  },
  {
    "name": "[AVN]Gimli",
    "power": 96279538
  },
  {
    "name": "[HOE]Falls",
    "power": 96118980
  },
  {
    "name": "[ExU]I Leila |",
    "power": 96046982
  },
  {
    "name": "[ARC]Majyk",
    "power": 95851379
  },
  {
    "name": "[HOE]Ely",
    "power": 95818496
  },
  {
    "name": "[ARC]Sloth",
    "power": 95816583
  },
  {
    "name": "[ARC]Sigita",
    "power": 95465433
  },
  {
    "name": "[AVN]kanourek",
    "power": 94983185
  },
  {
    "name": "TAVNJkanourek",
    "power": 94983185
  },
  {
    "name": "[AVN]WooHoo",
    "power": 94718708
  },
  {
    "name": "[VLT]Rogue",
    "power": 94170215
  },
  {
    "name": "[ExU]GumGumBazooka",
    "power": 93974660
  },
  {
    "name": "[HOE]Red",
    "power": 92332054
  },
  {
    "name": "[ExU]Land Shark",
    "power": 92224780
  },
  {
    "name": "[AVN]AndoCommando850",
    "power": 76104891
  },
  {
    "name": "[HOE]Alec",
    "power": 91556277
  },
  {
    "name": "[AVN]Ser Arishem",
    "power": 42734591
  },
  {
    "name": "[HOE]Alfredo940",
    "power": 91098003
  },
  {
    "name": "[ExU]ABSOLUTE",
    "power": 90679515
  },
  {
    "name": "[ExU]sapiens 10",
    "power": 90596859
  },
  {
    "name": "[AVN]Suffocation",
    "power": 90568703
  },
  {
    "name": "[ExU]jingleLizard",
    "power": 90446261
  },
  {
    "name": "[AVN]Spicy",
    "power": 90273022
  },
  {
    "name": "[HOE]aelin",
    "power": 90130190
  },
  {
    "name": "[ExU]psy",
    "power": 89815908
  },
  {
    "name": "[roj]y",
    "power": 5013700
  },
  {
    "name": "InocjJeo",
    "power": 89695347
  },
  {
    "name": "[ANT]omris",
    "power": 89462477
  },
  {
    "name": "JAVNjbORU",
    "power": 89099881
  },
  {
    "name": "[ExU]GEAR",
    "power": 88136792
  },
  {
    "name": "[ExU]Lea",
    "power": 88096160
  },
  {
    "name": "[ARC]Princess Lea",
    "power": 87773870
  },
  {
    "name": "[ARC]ady Viman",
    "power": 87700122
  },
  {
    "name": "[ARC]Mathjes",
    "power": 87685652
  },
  {
    "name": "[ARC]Lady Viman",
    "power": 87700122
  },
  {
    "name": "[ExU]Lord StrongOne",
    "power": 87589217
  },
  {
    "name": "[AVN]Zargothrax",
    "power": 87074639
  },
  {
    "name": "[ExU]Sayb",
    "power": 87058514
  },
  {
    "name": "[ExU]Mong1183",
    "power": 86891884
  },
  {
    "name": "[HOE]Manik",
    "power": 8651175
  },
  {
    "name": "[AVN]Zargothrax",
    "power": 74639870
  },
  {
    "name": "[HOE]mallis",
    "power": 86702064
  },
  {
    "name": "[HOE]Manik",
    "power": 86511175
  },
  {
    "name": "[ExU]Lord Byron XX",
    "power": 86271924
  },
  {
    "name": "[HOE]Cody",
    "power": 86224896
  }
]